{"v":"4.8.0","meta":{"g":"LottieFiles AE 3.4.4","a":"","k":"","d":"","tc":""},"fr":24,"ip":0,"op":48,"w":1080,"h":1080,"nm":"k-Lopping","ddd":0,"assets":[{"id":"comp_0","layers":[{"ddd":0,"ind":1,"ty":0,"nm":"Backword looping","refId":"comp_1","sr":1,"ks":{"o":{"a":0,"k":100,"ix":11},"r":{"a":0,"k":0,"ix":10},"p":{"a":0,"k":[540,540,0],"ix":2},"a":{"a":0,"k":[540,540,0],"ix":1},"s":{"a":0,"k":[100,100,100],"ix":6}},"ao":0,"w":1080,"h":1080,"ip":19,"op":47,"st":16,"bm":0},{"ddd":0,"ind":2,"ty":0,"nm":"Forword looping","refId":"comp_2","sr":1,"ks":{"o":{"a":0,"k":100,"ix":11},"r":{"a":0,"k":0,"ix":10},"p":{"a":0,"k":[540,540,0],"ix":2},"a":{"a":0,"k":[540,540,0],"ix":1},"s":{"a":0,"k":[100,100,100],"ix":6}},"ao":0,"w":1080,"h":1080,"ip":0,"op":23,"st":0,"bm":0}]},{"id":"comp_1","layers":[{"ddd":0,"ind":1,"ty":4,"nm":"Shape Layer 2","td":1,"sr":1,"ks":{"o":{"a":0,"k":100,"ix":11},"r":{"a":0,"k":0,"ix":10},"p":{"a":0,"k":[540,540,0],"ix":2},"a":{"a":0,"k":[0,0,0],"ix":1},"s":{"a":0,"k":[100,100,100],"ix":6}},"ao":0,"shapes":[{"ty":"gr","it":[{"ind":0,"ty":"sh","ix":1,"ks":{"a":0,"k":{"i":[[0,0],[0,0],[0,0]],"o":[[0,0],[0,0],[0,0]],"v":[[34,-122],[262,-122],[264,182]],"c":false},"ix":2},"nm":"Path 1","mn":"ADBE Vector Shape - Group","hd":false},{"ty":"st","c":{"a":0,"k":[0.4191279991,0.07211299971,0.649474977979,1],"ix":3},"o":{"a":0,"k":100,"ix":4},"w":{"a":0,"k":108,"ix":5},"lc":2,"lj":1,"ml":4,"bm":0,"nm":"Stroke 1","mn":"ADBE Vector Graphic - Stroke","hd":false},{"ty":"tr","p":{"a":0,"k":[0,0],"ix":2},"a":{"a":0,"k":[0,0],"ix":1},"s":{"a":0,"k":[100,100],"ix":3},"r":{"a":0,"k":0,"ix":6},"o":{"a":0,"k":100,"ix":7},"sk":{"a":0,"k":0,"ix":4},"sa":{"a":0,"k":0,"ix":5},"nm":"Transform"}],"nm":"Shape 1","np":3,"cix":2,"bm":0,"ix":1,"mn":"ADBE Vector Group","hd":false},{"ty":"tm","s":{"a":0,"k":0,"ix":1},"e":{"a":1,"k":[{"i":{"x":[0.667],"y":[1]},"o":{"x":[1],"y":[0]},"t":0,"s":[96]},{"t":15,"s":[0]}],"ix":2},"o":{"a":0,"k":0,"ix":3},"m":1,"ix":2,"nm":"Trim Paths 1","mn":"ADBE Vector Filter - Trim","hd":false}],"ip":0,"op":240,"st":0,"bm":0},{"ddd":0,"ind":2,"ty":4,"nm":"Layer 2 Outlines","tt":1,"sr":1,"ks":{"o":{"a":0,"k":100,"ix":11},"r":{"a":0,"k":0,"ix":10},"p":{"a":0,"k":[724.567,535.255,0],"ix":2},"a":{"a":0,"k":[125.043,155.671,0],"ix":1},"s":{"a":0,"k":[100,100,100],"ix":6}},"ao":0,"shapes":[{"ty":"gr","it":[{"ind":0,"ty":"sh","ix":1,"ks":{"a":0,"k":{"i":[[25.164,0],[0,25.164],[0,0],[0,0],[0,25.164],[-25.164,0],[0,0],[0,-25.163],[0,0]],"o":[[-25.163,0],[0,0],[0,0],[-25.164,0],[0,-25.163],[0,0],[25.164,0],[0,0],[0,25.164]],"v":[[79.227,155.421],[33.661,109.855],[33.661,-64.289],[-79.226,-64.289],[-124.793,-109.855],[-79.226,-155.421],[79.227,-155.421],[124.793,-109.855],[124.793,109.855]],"c":true},"ix":2},"nm":"Path 1","mn":"ADBE Vector Shape - Group","hd":false},{"ty":"fl","c":{"a":0,"k":[0.294117647059,0.117647058824,0.741176470588,1],"ix":4},"o":{"a":0,"k":100,"ix":5},"r":1,"bm":0,"nm":"Fill 1","mn":"ADBE Vector Graphic - Fill","hd":false},{"ty":"tr","p":{"a":0,"k":[125.043,155.671],"ix":2},"a":{"a":0,"k":[0,0],"ix":1},"s":{"a":0,"k":[100,100],"ix":3},"r":{"a":0,"k":0,"ix":6},"o":{"a":0,"k":100,"ix":7},"sk":{"a":0,"k":0,"ix":4},"sa":{"a":0,"k":0,"ix":5},"nm":"Transform"}],"nm":"Group 1","np":2,"cix":2,"bm":0,"ix":1,"mn":"ADBE Vector Group","hd":false}],"ip":0,"op":240,"st":0,"bm":0},{"ddd":0,"ind":4,"ty":4,"nm":"Shape Layer 1","td":1,"sr":1,"ks":{"o":{"a":0,"k":100,"ix":11},"r":{"a":0,"k":0,"ix":10},"p":{"a":0,"k":[540,540,0],"ix":2},"a":{"a":0,"k":[0,0,0],"ix":1},"s":{"a":0,"k":[100,100,100],"ix":6}},"ao":0,"shapes":[{"ty":"gr","it":[{"ind":0,"ty":"sh","ix":1,"ks":{"a":0,"k":{"i":[[0,0],[18,-22],[0,-112],[0,0],[-66,0],[0,0],[0,-6],[0,0],[0,0]],"o":[[0,0],[-18,22],[0,112],[0,0],[66,0],[0,0],[0,6],[0,0],[0,0]],"v":[[156,-374],[-165,-59],[-198,84],[-198,288],[-128,358],[30,358],[62,436],[68,-158],[62,-324]],"c":false},"ix":2},"nm":"Path 1","mn":"ADBE Vector Shape - Group","hd":false},{"ty":"st","c":{"a":0,"k":[0.4191279991,0.07211299971,0.649474977979,1],"ix":3},"o":{"a":0,"k":100,"ix":4},"w":{"a":0,"k":103,"ix":5},"lc":2,"lj":1,"ml":4,"bm":0,"nm":"Stroke 1","mn":"ADBE Vector Graphic - Stroke","hd":false},{"ty":"tr","p":{"a":0,"k":[0,0],"ix":2},"a":{"a":0,"k":[0,0],"ix":1},"s":{"a":0,"k":[100,100],"ix":3},"r":{"a":0,"k":0,"ix":6},"o":{"a":0,"k":100,"ix":7},"sk":{"a":0,"k":0,"ix":4},"sa":{"a":0,"k":0,"ix":5},"nm":"Transform"}],"nm":"Shape 1","np":3,"cix":2,"bm":0,"ix":1,"mn":"ADBE Vector Group","hd":false},{"ty":"tm","s":{"a":0,"k":0,"ix":1},"e":{"a":1,"k":[{"i":{"x":[0.262],"y":[1]},"o":{"x":[0.687],"y":[0]},"t":12,"s":[97]},{"t":24,"s":[0]}],"ix":2},"o":{"a":0,"k":0,"ix":3},"m":1,"ix":2,"nm":"Trim Paths 1","mn":"ADBE Vector Filter - Trim","hd":false}],"ip":0,"op":251,"st":11,"bm":0},{"ddd":0,"ind":5,"ty":4,"nm":"Layer 3 Outlines","tt":1,"sr":1,"ks":{"o":{"a":0,"k":100,"ix":11},"r":{"a":0,"k":0,"ix":10},"p":{"a":0,"k":[468.845,570.009,0],"ix":2},"a":{"a":0,"k":[176.773,399.455,0],"ix":1},"s":{"a":0,"k":[100,100,100],"ix":6}},"ao":0,"shapes":[{"ty":"gr","it":[{"ind":0,"ty":"sh","ix":1,"ks":{"a":0,"k":{"i":[[0,0],[12.759,0],[0,0],[0,12.667],[0,0],[-5.65,4.375],[-2.278,2.097],[0,0]],"o":[[0,12.667],[0,0],[-12.667,0],[0,0],[0,-7.109],[2.46,-1.822],[0,0],[0,0]],"v":[[85.392,262.324],[62.335,285.29],[-62.425,285.29],[-85.391,262.324],[-85.391,-21.917],[-76.368,-40.236],[-69.351,-46.068],[85.392,-189.966]],"c":true},"ix":2},"nm":"Path 1","mn":"ADBE Vector Shape - Group","hd":false},{"ind":1,"ty":"sh","ix":2,"ks":{"a":0,"k":{"i":[[0,0],[0,-35.633],[0,0],[-63.063,0],[0,0],[-8.749,2.097],[-18.135,0],[0,25.153],[0,0]],"o":[[-28.433,21.598],[0,0],[0,63.063],[0,0],[9.477,0],[7.29,15.402],[25.153,0],[0,0],[0,0]],"v":[[-131.412,-112.776],[-176.523,-21.917],[-176.523,262.324],[-62.425,376.422],[62.335,376.422],[89.765,373.14],[130.956,399.205],[176.523,353.638],[176.523,-399.205]],"c":true},"ix":2},"nm":"Path 2","mn":"ADBE Vector Shape - Group","hd":false},{"ty":"mm","mm":1,"nm":"Merge Paths 1","mn":"ADBE Vector Filter - Merge","hd":false},{"ty":"fl","c":{"a":0,"k":[0.294117647059,0.117647058824,0.741176470588,1],"ix":4},"o":{"a":0,"k":100,"ix":5},"r":1,"bm":0,"nm":"Fill 1","mn":"ADBE Vector Graphic - Fill","hd":false},{"ty":"tr","p":{"a":0,"k":[176.774,399.455],"ix":2},"a":{"a":0,"k":[0,0],"ix":1},"s":{"a":0,"k":[100,100],"ix":3},"r":{"a":0,"k":0,"ix":6},"o":{"a":0,"k":100,"ix":7},"sk":{"a":0,"k":0,"ix":4},"sa":{"a":0,"k":0,"ix":5},"nm":"Transform"}],"nm":"Group 1","np":4,"cix":2,"bm":0,"ix":1,"mn":"ADBE Vector Group","hd":false}],"ip":-6,"op":251,"st":11,"bm":0},{"ddd":0,"ind":7,"ty":4,"nm":"Shape Layer 3","td":1,"sr":1,"ks":{"o":{"a":0,"k":100,"ix":11},"r":{"a":0,"k":0,"ix":10},"p":{"a":0,"k":[540,548,0],"ix":2},"a":{"a":0,"k":[0,0,0],"ix":1},"s":{"a":0,"k":[100,100,100],"ix":6}},"ao":0,"shapes":[{"ty":"gr","it":[{"ind":0,"ty":"sh","ix":1,"ks":{"a":0,"k":{"i":[[0,0],[0,0]],"o":[[0,0],[0,0]],"v":[[-386,-346],[384,-346]],"c":false},"ix":2},"nm":"Path 1","mn":"ADBE Vector Shape - Group","hd":false},{"ty":"st","c":{"a":0,"k":[0.4191279991,0.07211299971,0.649474977979,1],"ix":3},"o":{"a":0,"k":100,"ix":4},"w":{"a":0,"k":108,"ix":5},"lc":2,"lj":1,"ml":4,"bm":0,"nm":"Stroke 1","mn":"ADBE Vector Graphic - Stroke","hd":false},{"ty":"tr","p":{"a":0,"k":[0,0],"ix":2},"a":{"a":0,"k":[0,0],"ix":1},"s":{"a":0,"k":[100,100],"ix":3},"r":{"a":0,"k":0,"ix":6},"o":{"a":0,"k":100,"ix":7},"sk":{"a":0,"k":0,"ix":4},"sa":{"a":0,"k":0,"ix":5},"nm":"Transform"}],"nm":"Shape 1","np":3,"cix":2,"bm":0,"ix":1,"mn":"ADBE Vector Group","hd":false},{"ty":"tm","s":{"a":0,"k":0,"ix":1},"e":{"a":1,"k":[{"i":{"x":[0.833],"y":[0.833]},"o":{"x":[0.167],"y":[0.167]},"t":21,"s":[100]},{"t":26,"s":[0]}],"ix":2},"o":{"a":0,"k":0,"ix":3},"m":1,"ix":2,"nm":"Trim Paths 1","mn":"ADBE Vector Filter - Trim","hd":false}],"ip":-18,"op":259,"st":19,"bm":0},{"ddd":0,"ind":8,"ty":4,"nm":"Layer 4 Outlines","parent":7,"tt":1,"sr":1,"ks":{"o":{"a":0,"k":100,"ix":11},"r":{"a":0,"k":0,"ix":10},"p":{"a":0,"k":[0,-341.892,0],"ix":2},"a":{"a":0,"k":[376.397,45.816,0],"ix":1},"s":{"a":0,"k":[100,100,100],"ix":6}},"ao":0,"shapes":[{"ty":"gr","it":[{"ind":0,"ty":"sh","ix":1,"ks":{"a":0,"k":{"i":[[25.164,0],[0,0],[0,25.164],[-25.163,0],[0,0],[0,-25.164]],"o":[[0,0],[-25.163,0],[0,-25.164],[0,0],[25.164,0],[0,25.164]],"v":[[330.582,45.566],[-330.581,45.566],[-376.147,0],[-330.581,-45.566],[330.582,-45.566],[376.147,0]],"c":true},"ix":2},"nm":"Path 1","mn":"ADBE Vector Shape - Group","hd":false},{"ty":"fl","c":{"a":0,"k":[0.294795227051,0.119169549381,0.741176470588,1],"ix":4},"o":{"a":0,"k":100,"ix":5},"r":1,"bm":0,"nm":"Fill 1","mn":"ADBE Vector Graphic - Fill","hd":false},{"ty":"tr","p":{"a":0,"k":[376.397,45.816],"ix":2},"a":{"a":0,"k":[0,0],"ix":1},"s":{"a":0,"k":[100,100],"ix":3},"r":{"a":0,"k":0,"ix":6},"o":{"a":0,"k":100,"ix":7},"sk":{"a":0,"k":0,"ix":4},"sa":{"a":0,"k":0,"ix":5},"nm":"Transform"}],"nm":"Group 1","np":2,"cix":2,"bm":0,"ix":1,"mn":"ADBE Vector Group","hd":false}],"ip":-16,"op":259,"st":19,"bm":0}]},{"id":"comp_2","layers":[{"ddd":0,"ind":1,"ty":4,"nm":"Shape Layer 2","td":1,"sr":1,"ks":{"o":{"a":0,"k":100,"ix":11},"r":{"a":0,"k":0,"ix":10},"p":{"a":0,"k":[540,540,0],"ix":2},"a":{"a":0,"k":[0,0,0],"ix":1},"s":{"a":0,"k":[100,100,100],"ix":6}},"ao":0,"shapes":[{"ty":"gr","it":[{"ind":0,"ty":"sh","ix":1,"ks":{"a":0,"k":{"i":[[0,0],[0,0],[0,0]],"o":[[0,0],[0,0],[0,0]],"v":[[34,-122],[262,-122],[264,182]],"c":false},"ix":2},"nm":"Path 1","mn":"ADBE Vector Shape - Group","hd":false},{"ty":"st","c":{"a":0,"k":[0.4191279991,0.07211299971,0.649474977979,1],"ix":3},"o":{"a":0,"k":100,"ix":4},"w":{"a":0,"k":108,"ix":5},"lc":2,"lj":1,"ml":4,"bm":0,"nm":"Stroke 1","mn":"ADBE Vector Graphic - Stroke","hd":false},{"ty":"tr","p":{"a":0,"k":[0,0],"ix":2},"a":{"a":0,"k":[0,0],"ix":1},"s":{"a":0,"k":[100,100],"ix":3},"r":{"a":0,"k":0,"ix":6},"o":{"a":0,"k":100,"ix":7},"sk":{"a":0,"k":0,"ix":4},"sa":{"a":0,"k":0,"ix":5},"nm":"Transform"}],"nm":"Shape 1","np":3,"cix":2,"bm":0,"ix":1,"mn":"ADBE Vector Group","hd":false},{"ty":"tm","s":{"a":0,"k":0,"ix":1},"e":{"a":1,"k":[{"i":{"x":[0],"y":[1]},"o":{"x":[0.333],"y":[0]},"t":12,"s":[0]},{"t":26,"s":[96]}],"ix":2},"o":{"a":0,"k":0,"ix":3},"m":1,"ix":2,"nm":"Trim Paths 1","mn":"ADBE Vector Filter - Trim","hd":false}],"ip":11,"op":251,"st":11,"bm":0},{"ddd":0,"ind":2,"ty":4,"nm":"Layer 2 Outlines","tt":1,"sr":1,"ks":{"o":{"a":0,"k":100,"ix":11},"r":{"a":0,"k":0,"ix":10},"p":{"a":0,"k":[724.567,535.255,0],"ix":2},"a":{"a":0,"k":[125.043,155.671,0],"ix":1},"s":{"a":0,"k":[100,100,100],"ix":6}},"ao":0,"shapes":[{"ty":"gr","it":[{"ind":0,"ty":"sh","ix":1,"ks":{"a":0,"k":{"i":[[25.164,0],[0,25.164],[0,0],[0,0],[0,25.164],[-25.164,0],[0,0],[0,-25.163],[0,0]],"o":[[-25.163,0],[0,0],[0,0],[-25.164,0],[0,-25.163],[0,0],[25.164,0],[0,0],[0,25.164]],"v":[[79.227,155.421],[33.661,109.855],[33.661,-64.289],[-79.226,-64.289],[-124.793,-109.855],[-79.226,-155.421],[79.227,-155.421],[124.793,-109.855],[124.793,109.855]],"c":true},"ix":2},"nm":"Path 1","mn":"ADBE Vector Shape - Group","hd":false},{"ty":"fl","c":{"a":0,"k":[0.294117647059,0.117647058824,0.741176470588,1],"ix":4},"o":{"a":0,"k":100,"ix":5},"r":1,"bm":0,"nm":"Fill 1","mn":"ADBE Vector Graphic - Fill","hd":false},{"ty":"tr","p":{"a":0,"k":[125.043,155.671],"ix":2},"a":{"a":0,"k":[0,0],"ix":1},"s":{"a":0,"k":[100,100],"ix":3},"r":{"a":0,"k":0,"ix":6},"o":{"a":0,"k":100,"ix":7},"sk":{"a":0,"k":0,"ix":4},"sa":{"a":0,"k":0,"ix":5},"nm":"Transform"}],"nm":"Group 1","np":2,"cix":2,"bm":0,"ix":1,"mn":"ADBE Vector Group","hd":false}],"ip":3,"op":243,"st":3,"bm":0},{"ddd":0,"ind":4,"ty":4,"nm":"Shape Layer 1","td":1,"sr":1,"ks":{"o":{"a":0,"k":100,"ix":11},"r":{"a":0,"k":0,"ix":10},"p":{"a":0,"k":[540,540,0],"ix":2},"a":{"a":0,"k":[0,0,0],"ix":1},"s":{"a":0,"k":[100,100,100],"ix":6}},"ao":0,"shapes":[{"ty":"gr","it":[{"ind":0,"ty":"sh","ix":1,"ks":{"a":0,"k":{"i":[[0,0],[20.1,-20.1],[0,-112],[0,0],[-66,0],[0,0],[0,-6],[0,0],[0,0]],"o":[[0,0],[-26.5,26.5],[0,112],[0,0],[66,0],[0,0],[0,6],[0,0],[0,0]],"v":[[153,-362],[-168,-60],[-198,96],[-198,288],[-128,358],[30,358],[62,436],[68,-158],[62,-324]],"c":false},"ix":2},"nm":"Path 1","mn":"ADBE Vector Shape - Group","hd":false},{"ty":"st","c":{"a":0,"k":[0.4191279991,0.07211299971,0.649474977979,1],"ix":3},"o":{"a":0,"k":100,"ix":4},"w":{"a":0,"k":103,"ix":5},"lc":2,"lj":1,"ml":4,"bm":0,"nm":"Stroke 1","mn":"ADBE Vector Graphic - Stroke","hd":false},{"ty":"tr","p":{"a":0,"k":[0,0],"ix":2},"a":{"a":0,"k":[0,0],"ix":1},"s":{"a":0,"k":[100,100],"ix":3},"r":{"a":0,"k":0,"ix":6},"o":{"a":0,"k":100,"ix":7},"sk":{"a":0,"k":0,"ix":4},"sa":{"a":0,"k":0,"ix":5},"nm":"Transform"}],"nm":"Shape 1","np":3,"cix":2,"bm":0,"ix":1,"mn":"ADBE Vector Group","hd":false},{"ty":"tm","s":{"a":0,"k":0,"ix":1},"e":{"a":1,"k":[{"i":{"x":[0.313],"y":[1]},"o":{"x":[0.738],"y":[0]},"t":4,"s":[0]},{"t":16,"s":[97]}],"ix":2},"o":{"a":0,"k":0,"ix":3},"m":1,"ix":2,"nm":"Trim Paths 1","mn":"ADBE Vector Filter - Trim","hd":false}],"ip":3,"op":243,"st":3,"bm":0},{"ddd":0,"ind":5,"ty":4,"nm":"Layer 3 Outlines","tt":1,"sr":1,"ks":{"o":{"a":0,"k":100,"ix":11},"r":{"a":0,"k":0,"ix":10},"p":{"a":0,"k":[468.845,570.009,0],"ix":2},"a":{"a":0,"k":[176.773,399.455,0],"ix":1},"s":{"a":0,"k":[100,100,100],"ix":6}},"ao":0,"shapes":[{"ty":"gr","it":[{"ind":0,"ty":"sh","ix":1,"ks":{"a":0,"k":{"i":[[0,0],[12.759,0],[0,0],[0,12.667],[0,0],[-5.65,4.375],[-2.278,2.097],[0,0]],"o":[[0,12.667],[0,0],[-12.667,0],[0,0],[0,-7.109],[2.46,-1.822],[0,0],[0,0]],"v":[[85.392,262.324],[62.335,285.29],[-62.425,285.29],[-85.391,262.324],[-85.391,-21.917],[-76.368,-40.236],[-69.351,-46.068],[85.392,-189.966]],"c":true},"ix":2},"nm":"Path 1","mn":"ADBE Vector Shape - Group","hd":false},{"ind":1,"ty":"sh","ix":2,"ks":{"a":0,"k":{"i":[[0,0],[0,-35.633],[0,0],[-63.063,0],[0,0],[-8.749,2.097],[-18.135,0],[0,25.153],[0,0]],"o":[[-28.433,21.598],[0,0],[0,63.063],[0,0],[9.477,0],[7.29,15.402],[25.153,0],[0,0],[0,0]],"v":[[-131.412,-112.776],[-176.523,-21.917],[-176.523,262.324],[-62.425,376.422],[62.335,376.422],[89.765,373.14],[130.956,399.205],[176.523,353.638],[176.523,-399.205]],"c":true},"ix":2},"nm":"Path 2","mn":"ADBE Vector Shape - Group","hd":false},{"ty":"mm","mm":1,"nm":"Merge Paths 1","mn":"ADBE Vector Filter - Merge","hd":false},{"ty":"fl","c":{"a":0,"k":[0.294117647059,0.117647058824,0.741176470588,1],"ix":4},"o":{"a":0,"k":100,"ix":5},"r":1,"bm":0,"nm":"Fill 1","mn":"ADBE Vector Graphic - Fill","hd":false},{"ty":"tr","p":{"a":0,"k":[176.774,399.455],"ix":2},"a":{"a":0,"k":[0,0],"ix":1},"s":{"a":0,"k":[100,100],"ix":3},"r":{"a":0,"k":0,"ix":6},"o":{"a":0,"k":100,"ix":7},"sk":{"a":0,"k":0,"ix":4},"sa":{"a":0,"k":0,"ix":5},"nm":"Transform"}],"nm":"Group 1","np":4,"cix":2,"bm":0,"ix":1,"mn":"ADBE Vector Group","hd":false}],"ip":3,"op":243,"st":3,"bm":0},{"ddd":0,"ind":7,"ty":4,"nm":"Shape Layer 3","td":1,"sr":1,"ks":{"o":{"a":0,"k":100,"ix":11},"r":{"a":0,"k":0,"ix":10},"p":{"a":0,"k":[540,548,0],"ix":2},"a":{"a":0,"k":[0,0,0],"ix":1},"s":{"a":0,"k":[100,100,100],"ix":6}},"ao":0,"shapes":[{"ty":"gr","it":[{"ind":0,"ty":"sh","ix":1,"ks":{"a":0,"k":{"i":[[0,0],[0,0]],"o":[[0,0],[0,0]],"v":[[-386,-346],[384,-346]],"c":false},"ix":2},"nm":"Path 1","mn":"ADBE Vector Shape - Group","hd":false},{"ty":"st","c":{"a":0,"k":[0.4191279991,0.07211299971,0.649474977979,1],"ix":3},"o":{"a":0,"k":100,"ix":4},"w":{"a":0,"k":108,"ix":5},"lc":2,"lj":1,"ml":4,"bm":0,"nm":"Stroke 1","mn":"ADBE Vector Graphic - Stroke","hd":false},{"ty":"tr","p":{"a":0,"k":[0,0],"ix":2},"a":{"a":0,"k":[0,0],"ix":1},"s":{"a":0,"k":[100,100],"ix":3},"r":{"a":0,"k":0,"ix":6},"o":{"a":0,"k":100,"ix":7},"sk":{"a":0,"k":0,"ix":4},"sa":{"a":0,"k":0,"ix":5},"nm":"Transform"}],"nm":"Shape 1","np":3,"cix":2,"bm":0,"ix":1,"mn":"ADBE Vector Group","hd":false},{"ty":"tm","s":{"a":0,"k":0,"ix":1},"e":{"a":1,"k":[{"i":{"x":[0.833],"y":[0.833]},"o":{"x":[0.167],"y":[0.167]},"t":0,"s":[0]},{"t":7,"s":[100]}],"ix":2},"o":{"a":0,"k":0,"ix":3},"m":1,"ix":2,"nm":"Trim Paths 1","mn":"ADBE Vector Filter - Trim","hd":false}],"ip":0,"op":240,"st":0,"bm":0},{"ddd":0,"ind":8,"ty":4,"nm":"Layer 4 Outlines","parent":7,"tt":1,"sr":1,"ks":{"o":{"a":0,"k":100,"ix":11},"r":{"a":0,"k":0,"ix":10},"p":{"a":0,"k":[0,-341.892,0],"ix":2},"a":{"a":0,"k":[376.397,45.816,0],"ix":1},"s":{"a":0,"k":[100,100,100],"ix":6}},"ao":0,"shapes":[{"ty":"gr","it":[{"ind":0,"ty":"sh","ix":1,"ks":{"a":0,"k":{"i":[[25.164,0],[0,0],[0,25.164],[-25.163,0],[0,0],[0,-25.164]],"o":[[0,0],[-25.163,0],[0,-25.164],[0,0],[25.164,0],[0,25.164]],"v":[[330.582,45.566],[-330.581,45.566],[-376.147,0],[-330.581,-45.566],[330.582,-45.566],[376.147,0]],"c":true},"ix":2},"nm":"Path 1","mn":"ADBE Vector Shape - Group","hd":false},{"ty":"fl","c":{"a":0,"k":[0.294795227051,0.119169549381,0.741176470588,1],"ix":4},"o":{"a":0,"k":100,"ix":5},"r":1,"bm":0,"nm":"Fill 1","mn":"ADBE Vector Graphic - Fill","hd":false},{"ty":"tr","p":{"a":0,"k":[376.397,45.816],"ix":2},"a":{"a":0,"k":[0,0],"ix":1},"s":{"a":0,"k":[100,100],"ix":3},"r":{"a":0,"k":0,"ix":6},"o":{"a":0,"k":100,"ix":7},"sk":{"a":0,"k":0,"ix":4},"sa":{"a":0,"k":0,"ix":5},"nm":"Transform"}],"nm":"Group 1","np":2,"cix":2,"bm":0,"ix":1,"mn":"ADBE Vector Group","hd":false}],"ip":0,"op":240,"st":0,"bm":0}]},{"id":"comp_3","layers":[{"ddd":0,"ind":1,"ty":0,"nm":"Backword looping","refId":"comp_1","sr":1,"ks":{"o":{"a":0,"k":100,"ix":11},"r":{"a":0,"k":0,"ix":10},"p":{"a":0,"k":[540,540,0],"ix":2},"a":{"a":0,"k":[540,540,0],"ix":1},"s":{"a":0,"k":[100,100,100],"ix":6}},"ao":0,"w":1080,"h":1080,"ip":19,"op":47,"st":16,"bm":0},{"ddd":0,"ind":2,"ty":0,"nm":"Forword looping","refId":"comp_2","sr":1,"ks":{"o":{"a":0,"k":100,"ix":11},"r":{"a":0,"k":0,"ix":10},"p":{"a":0,"k":[540,540,0],"ix":2},"a":{"a":0,"k":[540,540,0],"ix":1},"s":{"a":0,"k":[100,100,100],"ix":6}},"ao":0,"w":1080,"h":1080,"ip":0,"op":23,"st":0,"bm":0}]}],"layers":[{"ddd":0,"ind":1,"ty":0,"nm":"Loading active","refId":"comp_0","sr":1,"ks":{"o":{"a":0,"k":100,"ix":11},"r":{"a":0,"k":0,"ix":10},"p":{"a":0,"k":[540,540,0],"ix":2},"a":{"a":0,"k":[540,540,0],"ix":1},"s":{"a":0,"k":[100,100,100],"ix":6}},"ao":0,"w":1080,"h":1080,"ip":0,"op":48,"st":0,"bm":0},{"ddd":0,"ind":2,"ty":0,"nm":"Loading muted","td":1,"refId":"comp_3","sr":1,"ks":{"o":{"a":0,"k":100,"ix":11},"r":{"a":0,"k":0,"ix":10},"p":{"a":0,"k":[540,540,0],"ix":2},"a":{"a":0,"k":[540,540,0],"ix":1},"s":{"a":0,"k":[100,100,100],"ix":6}},"ao":0,"tm":{"a":0,"k":0.917,"ix":2},"w":1080,"h":1080,"ip":0,"op":48,"st":0,"bm":0},{"ddd":0,"ind":3,"ty":4,"nm":"Shape Layer 1","tt":1,"sr":1,"ks":{"o":{"a":0,"k":100,"ix":11},"r":{"a":0,"k":0,"ix":10},"p":{"a":0,"k":[540,540,0],"ix":2},"a":{"a":0,"k":[0,0,0],"ix":1},"s":{"a":0,"k":[100,100,100],"ix":6}},"ao":0,"shapes":[{"ty":"gr","it":[{"ty":"rc","d":1,"s":{"a":0,"k":[856,840],"ix":2},"p":{"a":0,"k":[0,0],"ix":3},"r":{"a":0,"k":0,"ix":4},"nm":"Rectangle Path 1","mn":"ADBE Vector Shape - Rect","hd":false},{"ty":"fl","c":{"a":0,"k":[0.756862745098,0.756862745098,0.756862745098,1],"ix":4},"o":{"a":0,"k":100,"ix":5},"r":1,"bm":0,"nm":"Fill 1","mn":"ADBE Vector Graphic - Fill","hd":false},{"ty":"tr","p":{"a":0,"k":[36,16],"ix":2},"a":{"a":0,"k":[0,0],"ix":1},"s":{"a":0,"k":[100,100],"ix":3},"r":{"a":0,"k":0,"ix":6},"o":{"a":0,"k":100,"ix":7},"sk":{"a":0,"k":0,"ix":4},"sa":{"a":0,"k":0,"ix":5},"nm":"Transform"}],"nm":"Rectangle 1","np":3,"cix":2,"bm":0,"ix":1,"mn":"ADBE Vector Group","hd":false}],"ip":0,"op":240,"st":0,"bm":0}],"markers":[]}